converters/__init__.py
converters/to_onnx.py
retinaface/__init__.py
retinaface/box_utils.py
retinaface/data_augment.py
retinaface/dataset.py
retinaface/inference.py
retinaface/multibox_loss.py
retinaface/net.py
retinaface/network.py
retinaface/pre_trained_models.py
retinaface/predict_single.py
retinaface/prior_box.py
retinaface/train.py
retinaface/utils.py
retinaface_pytorch-0.0.8.dist-info/LICENSE
retinaface_pytorch-0.0.8.dist-info/METADATA
retinaface_pytorch-0.0.8.dist-info/WHEEL
retinaface_pytorch-0.0.8.dist-info/top_level.txt
retinaface_pytorch-0.0.8.dist-info/RECORD
