Metadata-Version: 2.1
Name: retinaface-pytorch
Version: 0.0.8
Summary: Retinaface implementation in Pytorch.
Home-page: https://github.com/ternaus/retinaface
Author: Vladimir Iglovikov
License: MIT
Platform: UNKNOWN
Classifier: License :: OSI Approved :: MIT License
Classifier: Intended Audience :: Developers
Classifier: Intended Audience :: Science/Research
Classifier: Operating System :: OS Independent
Classifier: Programming Language :: Python
Classifier: Programming Language :: Python :: 3
Classifier: Topic :: Software Development :: Libraries
Classifier: Topic :: Software Development :: Libraries :: Python Modules
Requires-Dist: albumentations (==1.0.0)
Requires-Dist: torch (==1.9.0)
Requires-Dist: torchvision (==0.10.0)
Provides-Extra: test
Requires-Dist: pytest ; extra == 'test'
